python_rule_engine/__init__.py
python_rule_engine/decoder.py
python_rule_engine/engine.py
python_rule_engine/errors.py
python_rule_engine/json_path.py
python_rule_engine/models/__init__.py
python_rule_engine/models/condition.py
python_rule_engine/models/multi_condition.py
python_rule_engine/models/rule.py
python_rule_engine/models/simple_condition.py
python_rule_engine/operators.py
python_rule_engine-1.0.0.dist-info/LICENSE.txt
python_rule_engine-1.0.0.dist-info/METADATA
python_rule_engine-1.0.0.dist-info/WHEEL
python_rule_engine-1.0.0.dist-info/RECORD
