Metadata-Version: 2.3
Name: python-rule-engine
Version: 1.0.0
Summary: A rule engine where rules are written in JSON format
License: MIT
Keywords: rule-engine,rules,json,python
Author: Santiago Alvarez
Author-email: santiago.salvarez@mercadolibre.com
Requires-Python: >=3.9,<4.0
Classifier: Environment :: Console
Classifier: Intended Audience :: Developers
Classifier: License :: OSI Approved :: MIT License
Classifier: Operating System :: OS Independent
Classifier: Programming Language :: Python
Classifier: Programming Language :: Python :: 3
Classifier: Programming Language :: Python :: 3.9
Classifier: Programming Language :: Python :: 3.10
Classifier: Programming Language :: Python :: 3.11
Classifier: Programming Language :: Python :: 3.12
Classifier: Programming Language :: Python :: 3.13
Classifier: Topic :: Software Development :: Libraries :: Application Frameworks
Requires-Dist: jsonpath-ng (>=1.5.3,<2.0.0)
Requires-Dist: pydantic (>=2.10.6,<3.0.0)
Requires-Dist: pydantic-core (>=2.29.0,<3.0.0)
Project-URL: Homepage, https://github.com/santalvarez/python-rule-engine
